[{"id":"5.CS24.DA.3","title":"5.DA.3","text":"The student will explain the significance of training data in machine learning.","grade":"Grade 5","strand":"Data & Analysis","subject":"Computer Science (2024)","course":"Computer Science (2024)","subs":["Compare how training data is utilized in supervised, unsupervised and reinforcement learning.","Explain how training data is used to make classification predictions.","Discuss the need and significance of diverse, inclusive, and large datasets."]}]