[{"id":"6.CS24.CSY.3","title":"6.CSY.3","text":"The student will identify and describe Artificial Intelligence (AI).","grade":"Grade 6","strand":"Computing Systems","subject":"Computer Science (2024)","course":"Computer Science (2024)","subs":["Define artificial intelligence and identify the characteristics of artificial intelligence.","Describe how AI technologies generate information or automate decision and how people interact with AI technologies.","Define algorithmic bias and explain its consequences on AI technologies and systems."]}]