[{"id":"6.SC.SC.7","title":6.7,"text":"The student will investigate and understand that air has properties and that Earth’s atmosphere has structure and is dynamic. Key ideas include","subject":"Science","course":"Science","subs":["air is a mixture of gaseous elements and compounds;","the atmosphere has physical characteristics;","properties of the atmosphere change with altitude;","there is a relationship between air movement, thermal energy, and weather conditions;","atmospheric measures are used to predict weather conditions; and","weather maps give basic information about fronts, systems, and weather measurements."]}]