[{"id":"6.SC.SC.9","title":6.9,"text":"The student will investigate and understand that humans impact the environment and individuals can influence public policy decisions related to energy and the environment. Key ideas include","subject":"Science","course":"Science","subs":["natural resources are important to protect and maintain;","renewable and nonrenewable resources can be managed;","major health and safety issues are associated with air and water quality;","major health and safety issues are related to different forms of energy;","preventive measures can protect land-use and reduce environmental hazards; and","there are cost/benefit tradeoffs in conservation policies."]}]