[{"id":"8.CS24.AP.2","title":"8.AP.2","text":"The student will plan and implement algorithms that include sequencing, loops, variables, user input, conditional control structures, functions, and various data types.","grade":"Grade 8","strand":"Algorithms & Programming","subject":"Computer Science (2024)","course":"Computer Science (2024)","subs":["Describe the concept of input and output of various data types for use in a computer program.","Plan an algorithm using plain language, pseudocode, or diagrams.","Write and test algorithms expressed using block-based or text-based programming languages."]}]