[{"id":"HS.DS.CXT.1","title":"DS.1","text":"The student will identify specific examples of real-world problems that can be effectively addressed using data science.","strand":"Data in Context","subject":"Data Science","course":"Data Science","subs":[]},{"id":"HS.DS.CXT.2","title":"DS.2","text":"The student will be able to formulate a top down plan for data collection and analysis, with quantifiable results, based on the context of a problem.","strand":"Data in Context","subject":"Data Science","course":"Data Science","subs":[]}]