[{"id":"K.VA.CP.1","title":"K.1","text":"The student will apply creative thinking to artmaking.","grade":"Kindergarten","strand":"Creative Process","subject":"Visual Art","course":"Visual Art","subs":["Draw from imagination","Create works of art that represent personal responses to art-making challenges."]},{"id":"K.VA.CP.1","title":"K.16","text":"The student will create artworks inspired by a variety of sources and subjects.","grade":"Kindergarten","strand":"Creative Process","subject":"Visual Art","course":"Visual Art","subs":["Depict the human figure.","Use nature as inspiration."]}]