{"content":"\n<h2>Overview</h2>\n<p>See all of the K-3 computer science standards by each strand and how they advance through early elementary school.</p>\n","frontmatter":{"title":"K-3 CS Vertical Articulation Chart","links":{"drive":"https://docs.google.com/document/d/1-cbkynwUsI5AG6oUvp8pG-0geQ7FGeiXIeelJl3_4LQ/edit?usp=drive_link","goopen":"https://goopenva.org/courseware/lesson/6486/overview"},"grades":["K-3"],"standards":["K-3.CS"],"pathData":{"exists":true,"path":"integration-toolkit/vertical-articulation/0-3.md"},"authors":"CodeVA Curriculum","subjects":["Computer Science"],"license":{"name":"CC-BY-NC-SA","link":"https://creativecommons.org/licenses/by-nc-sa/4.0/"},"tags":["integration","crosswalk","computer science"],"types":["Curricular Resource"],"audiences":["Classroom Teachers","Administrators","Curriculum Writers"],"image":"default.png","parents":[{"title":"Vertical Articulation Charts","links":{"drive":"https://drive.google.com/drive/folders/1Fs_Jo4R2xetmu8j1W7isyDUHrM14Y682","pdf":"https://drive.google.com/file/d/1xGWx5etH0u8qqRLxy_bFqFwJ0tzolItW/view?usp=drive_link"},"_tags":"vertical articulation","grades":"K-12","subjects":"Computer Science","contents":["./0-3.md","./2-5.md","./6-8.md","./algo.md","./systems.md","./cyber.md","./data.md","./impacts.md","./networks.md"],"pathData":{"exists":true,"path":"/integration-toolkit/vertical-articulation/meta.md"}},{"title":"CS Integration Toolkit","grades":"K-12","subjects":"Computer Science, English, Mathematics, Science, Visual Art, Music, Physical Education, Health, Social Studies","tags":"integration, crosswalk, computer science","types":"Curricular Resource","audiences":"Classroom Teachers, Administrators, Curriculum Writers","links":{"drive":"https://drive.google.com/drive/folders/1THJdRsCcKrjXdBBL2sZkx5GG1FuNfnD7"},"contents":["alignment-guides","./pocket-guides","./vertical-articulation","./crosswalks","./vocab-cards.md"],"pathData":{"exists":true,"path":"/integration-toolkit/meta.md"}}],"members":[]}}